[
  {
      "title": "Lorem ipsum dolor sit amet consectetur adipisicing elit. Labore id, nihil voluptas corrupti enim excepturi modi necessitatibus earum? Odio consectetur a voluptates non. Sapiente temporibus dicta atque eos quis impedit!",
      "description": "Descripción de Tarea 28",
      "priority": "MEDIUM",
      "creationDate": "2023-03-02T20:35:43.164Z",
      "expiration": "2023-09-10T14:52:20.625Z",
      "state": "DONE",
      "tags": [
          "Tag1",
          "Tag2"
      ],
      "comments": [
          "Comentario Tarea 28",
          "Comentario Tarea 28"
      ],
      "uid": "86624131-d103-4497-a471-0fed7e72f772"
  },
  {
      "title": "Tarea 64",
      "description": "Descripción de Tarea 64",
      "priority": "HIGH",
      "creationDate": "2023-07-12T05:09:37.260Z",
      "expiration": "2023-10-27T12:47:52.947Z",
      "state": "PENDING",
      "tags": [
          "Tag4",
          "Tag7"
      ],
      "comments": [
          "Comentario Tarea 64",
          "Comentario Tarea 64"
      ],
      "uid": "2911bd60-c3e0-43c3-b28c-79a2ca78ea58"
  },
  {
      "title": "Tarea 18",
      "description": "Descripción de Tarea 18",
      "priority": "HIGH",
      "creationDate": "2023-05-28T14:59:16.331Z",
      "expiration": "2023-08-31T10:27:13.066Z",
      "state": "PENDING",
      "tags": [
          "Tag3",
          "Tag9"
      ],
      "comments": [
          "Comentario Tarea 18",
          "Comentario Tarea 18"
      ],
      "uid": "449c7f0b-fc7d-4693-9fe0-2983a54c8470"
  },
  {
      "title": "Tarea 53",
      "description": "Descripción de Tarea 53",
      "priority": "LOW",
      "creationDate": "2023-04-15T08:20:47.512Z",
      "expiration": "2023-11-25T18:30:32.873Z",
      "state": "PENDING",
      "tags": [
          "Tag5",
          "Tag8"
      ],
      "comments": [
          "Comentario Tarea 53",
          "Comentario Tarea 53"
      ],
      "uid": "f3b3cbdf-8ea8-4c36-83a3-4bfa5630ed0e"
  },
  {
      "title": "Tarea 77",
      "description": "Descripción de Tarea 77",
      "priority": "MEDIUM",
      "creationDate": "2023-06-20T13:45:58.199Z",
      "expiration": "2023-09-05T11:15:21.664Z",
      "state": "PENDING",
      "tags": [
          "Tag2",
          "Tag6"
      ],
      "comments": [
          "Comentario Tarea 77",
          "Comentario Tarea 77"
      ],
      "uid": "af57779e-e743-4a38-8b80-472d1db3d248"
  },
  {
      "title": "Tarea 42",
      "description": "Descripción de Tarea 42",
      "priority": "HIGH",
      "creationDate": "2023-05-07T10:12:36.327Z",
      "expiration": "2023-12-10T20:40:19.782Z",
      "state": "DONE",
      "tags": [
          "Tag1",
          "Tag7"
      ],
      "comments": [
          "Comentario Tarea 42",
          "Comentario Tarea 42"
      ],
      "uid": "96fdef4f-8d27-4a3b-90b5-c512a0661ded"
  },
  {
      "title": "Tarea 91",
      "description": "Descripción de Tarea 91",
      "priority": "MEDIUM",
      "creationDate": "2023-02-25T16:58:54.578Z",
      "expiration": "2023-11-03T13:01:46.942Z",
      "state": "PENDING",
      "tags": [
          "Tag3",
          "Tag9"
      ],
      "comments": [
          "Comentario Tarea 91",
          "Comentario Tarea 91"
      ],
      "uid": "25dc534b-c1bb-4aa5-948f-da46cffce27c"
  },
  {
      "title": "Tarea 19",
      "description": "Descripción de Tarea 19",
      "priority": "LOW",
      "creationDate": "2023-03-10T22:09:10.815Z",
      "expiration": "2023-10-17T09:24:07.267Z",
      "state": "PENDING",
      "tags": [
          "Tag4",
          "Tag5"
      ],
      "comments": [
          "Comentario Tarea 19",
          "Comentario Tarea 19"
      ],
      "uid": "fc46088e-10db-4a1f-97ad-481f1cb1fb04"
  },
  {
      "title": "Tarea 59",
      "description": "Descripción de Tarea 59",
      "priority": "LOW",
      "creationDate": "2023-01-08T19:12:30.641Z",
      "expiration": "2023-09-30T07:50:15.939Z",
      "state": "PENDING",
      "tags": [
          "Tag6",
          "Tag8"
      ],
      "comments": [
          "Comentario Tarea 59",
          "Comentario Tarea 59"
      ],
      "uid": "4359b47c-7311-4fd4-8661-770e2ed94304"
  },
  {
      "title": "Tarea 85",
      "description": "Descripción de Tarea 85",
      "priority": "HIGH",
      "creationDate": "2023-02-18T05:35:47.273Z",
      "expiration": "2023-11-15T22:37:11.528Z",
      "state": "DONE",
      "tags": [
          "Tag2",
          "Tag7"
      ],
      "comments": [
          "Comentario Tarea 85",
          "Comentario Tarea 85"
      ],
      "uid": "f85d4269-1f64-477d-94ac-41a7ebbb3306"
  },
  {
      "title": "Tarea 67",
      "description": "Descripción de Tarea 67",
      "priority": "MEDIUM",
      "creationDate": "2023-03-30T11:21:29.694Z",
      "expiration": "2023-09-20T19:10:44.101Z",
      "state": "PENDING",
      "tags": [
          "Tag1",
          "Tag4"
      ],
      "comments": [
          "Comentario Tarea 67",
          "Comentario Tarea 67"
      ],
      "uid": "bda6308f-93af-43ed-9488-042e2baac122"
  },
  {
      "title": "Tarea 55",
      "description": "Descripción de Tarea 55",
      "priority": "HIGH",
      "creationDate": "2023-04-28T16:07:13.921Z",
      "expiration": "2023-12-03T17:52:53.735Z",
      "state": "PENDING",
      "tags": [
          "Tag3",
          "Tag6"
      ],
      "comments": [
          "Comentario Tarea 55",
          "Comentario Tarea 55"
      ],
      "uid": "f0c504a2-784f-4369-993d-e5292df2ac5b"
  },
  {
      "title": "Tarea 73",
      "description": "Descripción de Tarea 73",
      "priority": "MEDIUM",
      "creationDate": "2023-01-15T14:45:02.487Z",
      "expiration": "2023-10-08T12:30:49.805Z",
      "state": "PENDING",
      "tags": [
          "Tag1",
          "Tag9"
      ],
      "comments": [
          "Comentario Tarea 73",
          "Comentario Tarea 73"
      ],
      "uid": "2eb1bd77-0e61-47ca-931e-8603622ba9f8"
  },
  {
      "title": "Tarea 11",
      "description": "Descripción de Tarea 11",
      "priority": "LOW",
      "creationDate": "2023-06-18T08:24:17.389Z",
      "expiration": "2023-11-28T15:59:45.722Z",
      "state": "PENDING",
      "tags": [
          "Tag4",
          "Tag7"
      ],
      "comments": [
          "Comentario Tarea 11",
          "Comentario Tarea 11"
      ],
      "uid": "23a3cd83-37d8-4b46-aaf3-3937a3de04d2"
  },
  {
      "title": "Tarea 12",
      "description": "Descripción de Tarea 12",
      "priority": "HIGH",
      "creationDate": "2023-05-07T12:41:32.124Z",
      "expiration": "2023-09-19T18:16:58.457Z",
      "state": "PENDING",
      "tags": [
          "Tag1",
          "Tag8"
      ],
      "comments": [
          "Comentario Tarea 12",
          "Comentario Tarea 12"
      ],
      "uid": "9e9200d6-ade5-4d19-9fa7-1a34bf57c03c"
  },
  {
      "title": "Tarea 13",
      "description": "Descripción de Tarea 13",
      "priority": "MEDIUM",
      "creationDate": "2023-03-12T14:56:28.852Z",
      "expiration": "2023-10-02T21:31:57.185Z",
      "state": "DONE",
      "tags": [
          "Tag3",
          "Tag6"
      ],
      "comments": [
          "Comentario Tarea 13",
          "Comentario Tarea 13"
      ],
      "uid": "af1cccc6-888b-4b1e-ad86-9e22ceab317e"
  },
  {
      "title": "Tarea 14",
      "description": "Descripción de Tarea 14",
      "priority": "HIGH",
      "creationDate": "2023-02-24T09:17:49.396Z",
      "expiration": "2023-12-07T16:53:16.729Z",
      "state": "PENDING",
      "tags": [
          "Tag2",
          "Tag5"
      ],
      "comments": [
          "Comentario Tarea 14",
          "Comentario Tarea 14"
      ],
      "uid": "7aafc303-b875-4bf1-a2e9-8094687c66cf"
  },
  {
      "title": "Tarea 15",
      "description": "Descripción de Tarea 15",
      "priority": "MEDIUM",
      "creationDate": "2023-04-29T11:32:01.033Z",
      "expiration": "2023-11-11T18:07:29.366Z",
      "state": "PENDING",
      "tags": [
          "Tag1",
          "Tag9"
      ],
      "comments": [
          "Comentario Tarea 15",
          "Comentario Tarea 15"
      ],
      "uid": "d7e8056f-d1b8-4963-90e1-c7a61bfde625"
  },
  {
      "title": "Tarea 16",
      "description": "Descripción de Tarea 16",
      "priority": "LOW",
      "creationDate": "2023-01-18T15:47:04.760Z",
      "expiration": "2023-10-29T22:22:32.093Z",
      "state": "DONE",
      "tags": [
          "Tag4",
          "Tag8"
      ],
      "comments": [
          "Comentario Tarea 16",
          "Comentario Tarea 16"
      ],
      "uid": "03cc3102-7425-45de-8fe5-3a1a6e2a4bfb"
  },
  {
      "title": "Tarea 17",
      "description": "Descripción de Tarea 17",
      "priority": "MEDIUM",
      "creationDate": "2023-07-05T18:02:13.489Z",
      "expiration": "2023-09-14T00:37:40.822Z",
      "state": "PENDING",
      "tags": [
          "Tag3",
          "Tag7"
      ],
      "comments": [
          "Comentario Tarea 17",
          "Comentario Tarea 17"
      ],
      "uid": "ecc5359b-7fa7-4fae-8177-ed32d34838e1"
  },
  {
      "title": "Tarea 18",
      "description": "Descripción de Tarea 18",
      "priority": "HIGH",
      "creationDate": "2023-08-23T12:14:34.120Z",
      "expiration": "2023-12-24T18:50:01.453Z",
      "state": "PENDING",
      "tags": [
          "Tag2",
          "Tag6"
      ],
      "comments": [
          "Comentario Tarea 18",
          "Comentario Tarea 18"
      ],
      "uid": "e6dfa506-69fa-441f-b1bd-f214071d00a9"
  },
  {
      "title": "Tarea 19",
      "description": "Descripción de Tarea 19",
      "priority": "LOW",
      "creationDate": "2023-09-13T15:29:45.754Z",
      "expiration": "2023-10-15T22:05:13.087Z",
      "state": "DONE",
      "tags": [
          "Tag1",
          "Tag5"
      ],
      "comments": [
          "Comentario Tarea 19",
          "Comentario Tarea 19"
      ],
      "uid": "2733676a-dea3-46d0-a235-9d9d035aafaa"
  },
  {
      "title": "Tarea 20",
      "description": "Descripción de Tarea 20",
      "priority": "MEDIUM",
      "creationDate": "2023-03-27T19:45:56.185Z",
      "expiration": "2023-11-02T02:21:23.518Z",
      "state": "PENDING",
      "tags": [
          "Tag4",
          "Tag9"
      ],
      "comments": [
          "Comentario Tarea 20",
          "Comentario Tarea 20"
      ],
      "uid": "e567c1b3-758d-4fdf-90a5-4fa35d18ecae"
  },
  {
      "title": "Tarea 21",
      "description": "Descripción de Tarea 21",
      "priority": "MEDIUM",
      "creationDate": "2023-05-15T08:30:00.000Z",
      "expiration": "2023-11-30T16:45:00.000Z",
      "state": "PENDING",
      "tags": [
          "Tag3",
          "Tag6"
      ],
      "comments": [
          "Comentario Tarea 21",
          "Comentario Tarea 21"
      ],
      "uid": "3619317a-da9a-460a-9d12-8e2e88f58ada"
  },
  {
      "title": "Tarea 22",
      "description": "Descripción de Tarea 22",
      "priority": "LOW",
      "creationDate": "2023-03-20T10:15:00.000Z",
      "expiration": "2023-10-10T14:20:00.000Z",
      "state": "PENDING",
      "tags": [
          "Tag1",
          "Tag4"
      ],
      "comments": [
          "Comentario Tarea 22",
          "Comentario Tarea 22"
      ],
      "uid": "590cd90a-1fe3-4ace-a7c9-8679166cc9e7"
  },
  {
      "title": "Tarea 23",
      "description": "Descripción de Tarea 23",
      "priority": "HIGH",
      "creationDate": "2023-07-10T15:45:00.000Z",
      "expiration": "2023-12-15T18:10:00.000Z",
      "state": "DONE",
      "tags": [
          "Tag2",
          "Tag5"
      ],
      "comments": [
          "Comentario Tarea 23",
          "Comentario Tarea 23"
      ],
      "uid": "33b73639-a778-45ce-bbe5-253ac99194a1"
  },
  {
      "title": "Tarea 24",
      "description": "Descripción de Tarea 24",
      "priority": "MEDIUM",
      "creationDate": "2023-02-05T09:00:00.000Z",
      "expiration": "2023-09-05T12:30:00.000Z",
      "state": "PENDING",
      "tags": [
          "Tag4",
          "Tag7"
      ],
      "comments": [
          "Comentario Tarea 24",
          "Comentario Tarea 24"
      ],
      "uid": "3efa083c-d4db-41c8-89f4-651209679de4"
  },
  {
      "title": "Tarea 25",
      "description": "Descripción de Tarea 25",
      "priority": "LOW",
      "creationDate": "2023-06-25T14:00:00.000Z",
      "expiration": "2023-11-20T16:15:00.000Z",
      "state": "PENDING",
      "tags": [
          "Tag1",
          "Tag8"
      ],
      "comments": [
          "Comentario Tarea 25",
          "Comentario Tarea 25"
      ],
      "uid": "34897a9d-89a3-494d-8a25-c87a02c660d0"
  },
  {
      "title": "Tarea 26",
      "description": "Descripción de Tarea 26",
      "priority": "HIGH",
      "creationDate": "2023-04-30T18:15:00.000Z",
      "expiration": "2023-12-01T20:30:00.000Z",
      "state": "DONE",
      "tags": [
          "Tag3",
          "Tag9"
      ],
      "comments": [
          "Comentario Tarea 26",
          "Comentario Tarea 26"
      ],
      "uid": "30dcfe8f-be94-4746-a3b6-24123694e877"
  },
  {
      "title": "Tarea 27",
      "description": "Descripción de Tarea 27",
      "priority": "MEDIUM",
      "creationDate": "2023-08-15T10:30:00.000Z",
      "expiration": "2023-10-25T12:45:00.000Z",
      "state": "PENDING",
      "tags": [
          "Tag2",
          "Tag7"
      ],
      "comments": [
          "Comentario Tarea 27",
          "Comentario Tarea 27"
      ],
      "uid": "5cb7d1c0-d968-475a-917b-ab3dc0a49995"
  },
  {
      "title": "Tarea 28",
      "description": "Descripción de Tarea 28",
      "priority": "HIGH",
      "creationDate": "2023-01-10T12:00:00.000Z",
      "expiration": "2023-09-15T14:15:00.000Z",
      "state": "PENDING",
      "tags": [
          "Tag1",
          "Tag6"
      ],
      "comments": [
          "Comentario Tarea 28",
          "Comentario Tarea 28"
      ],
      "uid": "1950165d-d47e-421f-9b66-c1881270cad2"
  },
  {
      "title": "Tarea 29",
      "description": "Descripción de Tarea 29",
      "priority": "LOW",
      "creationDate": "2023-09-05T16:45:00.000Z",
      "expiration": "2023-10-20T19:00:00.000Z",
      "state": "DONE",
      "tags": [
          "Tag4",
          "Tag8"
      ],
      "comments": [
          "Comentario Tarea 29",
          "Comentario Tarea 29"
      ],
      "uid": "be9266de-1d3d-4174-b594-202c29d25656"
  },
  {
      "title": "Tarea 30",
      "description": "Descripción de Tarea 30",
      "priority": "MEDIUM",
      "creationDate": "2023-03-15T11:30:00.000Z",
      "expiration": "2023-11-10T14:45:00.000Z",
      "state": "PENDING",
      "tags": [
          "Tag2",
          "Tag9"
      ],
      "comments": [
          "Comentario Tarea 30",
          "Comentario Tarea 30"
      ],
      "uid": "4abedf86-5bc7-4482-bef1-641eb3d3be2f"
  }
]
